puzzlecaptcha/__init__.py
puzzlecaptcha/apps.py
puzzlecaptcha/field.py
puzzlecaptcha/forms.py
puzzlecaptcha/templates/puzzlecaptcha/admin_login.html
puzzlecaptcha/templates/puzzlecaptcha/captcha.html
puzzlecaptcha/templates/puzzlecaptcha/captcha_image.html
puzzlecaptcha/templates/puzzlecaptcha/captcha_result.html
puzzlecaptcha/tests.py
django_puzzlecaptcha-0.1.1.dist-info/LICENSE
django_puzzlecaptcha-0.1.1.dist-info/METADATA
django_puzzlecaptcha-0.1.1.dist-info/WHEEL
django_puzzlecaptcha-0.1.1.dist-info/RECORD
