Metadata-Version: 2.1
Name: django-puzzlecaptcha
Version: 0.1.1
Summary: PuzzleCaptcha: Simplified Math CAPTCHA Using Pillow Image Library
License: MIT
Keywords: django,recaptcha,captcha,pillow,django-captcha
Author: Suraj Singh Bisht
Author-email: surajsinghbisht054@gmail.com
Classifier: License :: OSI Approved :: MIT License
Classifier: Programming Language :: Python :: 2
Classifier: Programming Language :: Python :: 2.7
Classifier: Programming Language :: Python :: 3
Classifier: Programming Language :: Python :: 3.4
Classifier: Programming Language :: Python :: 3.5
Classifier: Programming Language :: Python :: 3.6
Classifier: Programming Language :: Python :: 3.7
Classifier: Programming Language :: Python :: 3.8
Classifier: Programming Language :: Python :: 3.9
Classifier: Programming Language :: Python :: 3.10
Classifier: Programming Language :: Python :: 3.11
Classifier: Programming Language :: Python :: 3.12
Classifier: Programming Language :: Python :: 3.13
Requires-Dist: django (>=4.2)
Requires-Dist: numpy (>=2)
Requires-Dist: pillow (>=10)
